APISimplify/__init__.py
APISimplify/auth.py
APISimplify/bloxflip.py
APISimplify/discord.py
APISimplify/discordbot.py
APISimplify/easyapi.py
APISimplify/fortnite.py
APISimplify/github.py
APISimplify/instagram.py
APISimplify/libreview.py
APISimplify/roblox.py
APISimplify/spotify.py
APISimplify/steam.py
APISimplify/telegram.py
APISimplify/tiktok.py
APISimplify/twitter.py
APISimplify/utils.py
APISimplify/valorant.py
APISimplify/virustotal.py
APISimplify/whatsapp.py
APISimplify/xbox.py
APISimplify-0.0.6.dist-info/LICENSE
APISimplify-0.0.6.dist-info/METADATA
APISimplify-0.0.6.dist-info/WHEEL
APISimplify-0.0.6.dist-info/top_level.txt
APISimplify-0.0.6.dist-info/RECORD
