Metadata-Version: 2.1
Name: APISimplify
Version: 0.0.6
Summary: A simple API toolkit for Python developers
Author-email: master_wasdondiscord <masterioempo@gmail.com>
License: MIT License
Requires-Python: >=3.6.0
License-File: LICENSE
Requires-Dist: requests>=2.25.0
Requires-Dist: discord>=1.0.0
Requires-Dist: Pillow>=8.0.0
Requires-Dist: jsonschema>=3.2.0
